strimbul/__init__.py
strimbul/app.py
strimbul/create_files.py
strimbul/file1.py
strimbul/file2.py
strimbul/file3.py
strimbul/file4.py
strimbul/file5.py
strimbul/main.py
strimbul/plugins/__init__.py
strimbul/plugins/plugin1.py
strimbul/plugins/plugin2.py
strimbul/plugins/plugin3.py
strimbul/plugins/plugin4.py
strimbul/plugins/plugin5.py
strimbul-2.2.1.dist-info/METADATA
strimbul-2.2.1.dist-info/WHEEL
strimbul-2.2.1.dist-info/entry_points.txt
strimbul-2.2.1.dist-info/top_level.txt
strimbul-2.2.1.dist-info/RECORD
