Metadata-Version: 2.1
Name: strimbul
Version: 2.2.1
Requires-Dist: streamlit
